ipas/__init__.py
ipas/collection_from_db/__init__.py
ipas/collection_from_db/aggagg_collection.py
ipas/collection_from_db/batch_statistics.py
ipas/collection_from_db/calculations.py
ipas/collection_from_db/cluster.py
ipas/collection_from_db/crystal.py
ipas/collection_from_db/database.py
ipas/collection_from_db/iceagg_collection.py
ipas/collection_from_db/plot.py
ipas/collection_from_db/plotly_aggs.py
ipas/collection_no_db/__init__.py
ipas/collection_no_db/calculations.py
ipas/collection_no_db/cluster.py
ipas/collection_no_db/crystal.py
ipas/collection_no_db/iceagg_collection.py
ipas/collection_no_db/iceagg_collection_nodask.py
ipas/collection_no_db/iceice_collection.py
ipas/collection_no_db/plot.py
ipas/executables/__init__.py
ipas/executables/collection_no_db/Ice_Agg.py
ipas/executables/collection_no_db/Ice_Ice.py
ipas/executables/collection_no_db/__init__.py
ipas-2.1.2.dist-info/LICENSE.md
ipas-2.1.2.dist-info/METADATA
ipas-2.1.2.dist-info/WHEEL
ipas-2.1.2.dist-info/entry_points.txt
ipas-2.1.2.dist-info/top_level.txt
ipas-2.1.2.dist-info/RECORD
