Metadata-Version: 2.1
Name: ipas
Version: 2.1.2
Summary: Theoretically simulates ice crystal aggregation (snow) using hexagonal prisms
Home-page: https://github.com/vprzybylo/IPAS
Author: Vanessa Przybylo
Author-email: vprzybylo@albany.edu
License: MIT
Download-URL: https://github.com/vprzybylo/IPAS.git
Platform: UNKNOWN
Classifier: Development Status :: 3 - Alpha
Classifier: Programming Language :: Python :: 3.7
Classifier: License :: OSI Approved :: MIT License
Requires-Python: >=3.7
Requires-Dist: cytoolz
Requires-Dist: dask
Requires-Dist: dask-jobqueue
Requires-Dist: descartes
Requires-Dist: numpy
Requires-Dist: pandas
Requires-Dist: plotly
Requires-Dist: pyquaternion
Requires-Dist: QtPy
Requires-Dist: Shapely
Requires-Dist: scipy
Provides-Extra: dev
Requires-Dist: flakehell ; extra == 'dev'
Requires-Dist: ipympl ; extra == 'dev'
Requires-Dist: ipykernel ; extra == 'dev'
Requires-Dist: ipywidgets ; extra == 'dev'
Requires-Dist: jupyterlab ; extra == 'dev'
Requires-Dist: jupyter-server ; extra == 'dev'
Requires-Dist: jupyterlab-lsp ; extra == 'dev'
Requires-Dist: matplotlib ; extra == 'dev'
Requires-Dist: nbconvert ; extra == 'dev'
Requires-Dist: nbstripout ; extra == 'dev'
Requires-Dist: seaborn ; extra == 'dev'
